XStatic_Rickshaw-1.5.1.0-py3.6-nspkg.pth
xstatic/pkg/rickshaw/__init__.py
xstatic/pkg/rickshaw/data/rickshaw.css
xstatic/pkg/rickshaw/data/rickshaw.js
XStatic_Rickshaw-1.5.1.0.dist-info/METADATA
XStatic_Rickshaw-1.5.1.0.dist-info/WHEEL
XStatic_Rickshaw-1.5.1.0.dist-info/namespace_packages.txt
XStatic_Rickshaw-1.5.1.0.dist-info/top_level.txt
XStatic_Rickshaw-1.5.1.0.dist-info/RECORD
