Metadata-Version: 2.1
Name: XStatic-Rickshaw
Version: 1.5.1.0
Summary: Rickshaw 1.5.1 (XStatic packaging standard)
Home-page: http://code.shutterstock.com/rickshaw/
Maintainer: Radomir Dopieralski
Maintainer-email: openstack@sheep.art.pl
License: (same as Rickshaw)
Keywords: rickshaw xstatic
Platform: any
